genTest/__init__.py
genTest/__main__.py
unipa/__init__.py
unipa/errors.py
unipa/test_login.py
unipa/unipa_utils.py
unipa/BulletinBoard/BulletinBoard.py
unipa/BulletinBoard/BulletinBoardItemDetails.py
unipa/BulletinBoard/PublicationPeriod.py
unipa/BulletinBoard/__init__.py
unipa/Classes/UnipaClass.py
unipa/Classes/__init__.py
unipa/models/__init__.py
unipa/models/tests.py
get_unipa-0.8.0.dist-info/LICENSE
get_unipa-0.8.0.dist-info/METADATA
get_unipa-0.8.0.dist-info/WHEEL
get_unipa-0.8.0.dist-info/top_level.txt
get_unipa-0.8.0.dist-info/RECORD
